tone_deaf/__init__.py
tone_deaf/functions.py
tone_deaf/functionsdict.py
tone_deaf/message.py
tone_deaf/stack.py
tone_deaf/chords/__init__.py
tone_deaf/chords/a_chords.py
tone_deaf/chords/d_chords.py
tone_deaf/chords/e_chords.py
tone_deaf/chords/utils.py
tone_deaf-0.3.0.dist-info/DESCRIPTION.rst
tone_deaf-0.3.0.dist-info/METADATA
tone_deaf-0.3.0.dist-info/RECORD
tone_deaf-0.3.0.dist-info/WHEEL
tone_deaf-0.3.0.dist-info/entry_points.txt
tone_deaf-0.3.0.dist-info/metadata.json
tone_deaf-0.3.0.dist-info/top_level.txt
