Metadata-Version: 2.0
Name: tone-deaf
Version: 0.3.0
Summary: An interpreter for the tone-deaf programming language.
Home-page: https://github.com/kade-robertson/tone-deaf
Author: Kade Robertson
Author-email: kade@kaderobertson.pw
License: MIT
Keywords: tone deaf esoteric programming language interpreter
Platform: UNKNOWN
Classifier: Development Status :: 3 - Alpha
Classifier: Intended Audience :: Developers
Classifier: Intended Audience :: End Users/Desktop
Classifier: License :: OSI Approved :: MIT License
Classifier: Operating System :: OS Independent
Classifier: Programming Language :: Python :: 3
Classifier: Programming Language :: Python :: 3.4
Classifier: Programming Language :: Python :: 3.5
Classifier: Programming Language :: Python :: 3.6
Requires-Python: >=3.4, <4
